airflan/__init__.py
airflan/orchestrator.py
airflan/ui.py
airflan/core/__init__.py
airflan/core/context.py
airflan/core/executor.py
airflan/core/scheduler.py
airflan/core/task.py
airflan/monitoring/__init__.py
airflan/storage/__init__.py
airflan/storage/cache.py
airflan/storage/state.py
airflan_workflow-0.1.2.dist-info/METADATA
airflan_workflow-0.1.2.dist-info/WHEEL
airflan_workflow-0.1.2.dist-info/top_level.txt
airflan_workflow-0.1.2.dist-info/RECORD
