Metadata-Version: 2.4
Name: airflan-workflow
Version: 0.1.2
Summary: Enterprise-Grade Workflow Orchestration for Python
Author-email: El-Qajjam Mohammed <elqajjam@gmail.com>
Project-URL: Homepage, https://github.com/noobjam/airflan
Project-URL: Bug Tracker, https://github.com/noobjam/airflan/issues
Classifier: Programming Language :: Python :: 3
Classifier: License :: OSI Approved :: MIT License
Classifier: Operating System :: OS Independent
Requires-Python: >=3.8
Requires-Dist: loguru>=0.7.0
Requires-Dist: streamlit>=1.37.0
Requires-Dist: streamlit-agraph>=0.0.45
Requires-Dist: plotly>=5.18.0
Requires-Dist: networkx>=3.0
